README.md
setup.py
Nested_List.egg-info/PKG-INFO
Nested_List.egg-info/SOURCES.txt
Nested_List.egg-info/dependency_links.txt
Nested_List.egg-info/top_level.txt
array_ls/__init__.py
dict_ls/__init__.py
nested_list/__init__.py
nested_list.egg-info/PKG-INFO
nested_list.egg-info/SOURCES.txt
nested_list.egg-info/dependency_links.txt
nested_list.egg-info/top_level.txt
obj_ls/__init__.py