Metadata-Version: 1.1
Name: Nested-List
Version: 1.0.0
Summary: A nested list Tool which is pure Python.
Home-page: https://github.com/arukione/nested-list
Author: aruki
Author-email: zqljiebin@gmail.com
License: MIT
Keywords: Nested-List
Platform: UNKNOWN
Classifier: Intended Audience :: Developers
Classifier: License :: OSI Approved :: MIT License
Classifier: Operating System :: OS Independent
Classifier: Programming Language :: Python :: 3.4
Classifier: Programming Language :: Python :: 3.5
Classifier: Programming Language :: Python :: 3.6
Classifier: Programming Language :: Python :: 3.7
Classifier: Topic :: Software Development :: Libraries :: Python Modules
